sync_camera_disk/__init__.py
sync_camera_disk/config.py
sync_camera_disk/destination.py
sync_camera_disk/disks.py
sync_camera_disk/file.py
sync_camera_disk/filter_disks.py
sync_camera_disk/macos.py
sync_camera_disk/main.py
sync_camera_disk/operation.py
sync_camera_disk/source.py
sync_camera_disk/testing/__init__.py
sync_camera_disk/testing/examples.py
sync_camera_disk/testing/files/mac_diskutil_atem_extreme_iso_sdi.json
sync_camera_disk/testing/files/mac_diskutil_atomos_shogun_ultra.json
sync_camera_disk/testing/files/mac_diskutil_dji.json
sync_camera_disk/testing/files/mac_diskutil_dji_osmo_pocket.json
sync_camera_disk/testing/files/mac_diskutil_drobo.json
sync_camera_disk/testing/files/mac_diskutil_fujifilm_x100.json
sync_camera_disk/testing/files/mac_diskutil_gopro_10.json
sync_camera_disk/testing/files/mac_diskutil_insta360_go_2.json
sync_camera_disk/testing/files/mac_diskutil_insta360_one.json
sync_camera_disk/testing/files/mac_diskutil_sony_a7_iv.json
sync_camera_disk-0.8.1.dist-info/LICENSE
sync_camera_disk-0.8.1.dist-info/METADATA
sync_camera_disk-0.8.1.dist-info/WHEEL
sync_camera_disk-0.8.1.dist-info/entry_points.txt
sync_camera_disk-0.8.1.dist-info/RECORD
