Metadata-Version: 2.1
Name: sync-camera-disk
Version: 0.8.1
Summary: Sync files from camera SDs to different media
Home-page: https://github.com/micktwomey/sync-camera-disk/
License: MIT
Author: Michael Twomey
Author-email: mick@twomeylee.name
Requires-Python: >=3.11,<4.0
Classifier: License :: OSI Approved :: MIT License
Classifier: Programming Language :: Python :: 3
Classifier: Programming Language :: Python :: 3.11
Classifier: Programming Language :: Python :: 3.12
Requires-Dist: pydantic (>=1.10.9,<2.0.0)
Requires-Dist: pydantic-yaml (>=1.0.0a2,<2.0.0)
Requires-Dist: rich (>=13.4.1,<14.0.0)
Requires-Dist: structlog (>=23.1.0,<24.0.0)
Requires-Dist: typer (>=0.9.0,<0.10.0)
Requires-Dist: xdg-base-dirs (>=6.0.0,<7.0.0)
Project-URL: Repository, https://github.com/micktwomey/sync-camera-disk/
